tracks/__init__.py
tracks/trackset.py
tracks-0.1.1.dist-info/DESCRIPTION.rst
tracks-0.1.1.dist-info/METADATA
tracks-0.1.1.dist-info/RECORD
tracks-0.1.1.dist-info/WHEEL
tracks-0.1.1.dist-info/metadata.json
tracks-0.1.1.dist-info/top_level.txt
