Metadata-Version: 2.0
Name: tracks
Version: 0.1.1
Summary: Simple A/B testing for your backend
Home-page: https://github.com/underyx/tracks
Author: Bence Nagy
Author-email: bence@underyx.me
License: UNKNOWN
Download-URL: https://github.com/underyx/tracks/releases
Platform: UNKNOWN
Classifier: Development Status :: 3 - Alpha
Classifier: Environment :: Console
Classifier: License :: OSI Approved :: MIT License
Classifier: Operating System :: OS Independent
Classifier: Programming Language :: Python :: 3.5
